omuchatprovider/__init__.py
omuchatprovider/__main__.py
omuchatprovider/chatprovider.py
omuchatprovider/errors.py
omuchatprovider/helper.py
omuchatprovider/tasks.py
omuchatprovider/throttle.py
omuchatprovider/version.py
omuchatprovider/services/__init__.py
omuchatprovider/services/service.py
omuchatprovider/services/youtube/__init__.py
omuchatprovider/services/youtube/chat.py
omuchatprovider/services/youtube/const.py
omuchatprovider/services/youtube/youtube.py
omuchatprovider/services/youtube/youtubeapi.py
omuchatprovider/services/youtube/types/__init__.py
omuchatprovider/services/youtube/types/accessibility.py
omuchatprovider/services/youtube/types/chatactions.py
omuchatprovider/services/youtube/types/contents.py
omuchatprovider/services/youtube/types/continuations.py
omuchatprovider/services/youtube/types/frameworkupdates.py
omuchatprovider/services/youtube/types/image.py
omuchatprovider/services/youtube/types/live_chat.py
omuchatprovider/services/youtube/types/metadataactions.py
omuchatprovider/services/youtube/types/responsecontext.py
omuchatprovider/services/youtube/types/runs.py
omuchatprovider/services/youtube/types/simpletext.py
omuchatprovider/services/youtube/types/updated_metadata.py
omuchatprovider/services/youtube/types/urlendpoint.py
omuchatprovider/services/youtube/types/youtuberesponse.py
omuchatprovider/services/youtube/types/ytcfg.py
omuchatprovider/services/youtube/types/ytinitialdata.py
omuchatprovider-0.3.2.dist-info/METADATA
omuchatprovider-0.3.2.dist-info/WHEEL
omuchatprovider-0.3.2.dist-info/entry_points.txt
omuchatprovider-0.3.2.dist-info/RECORD
