Metadata-Version: 2.3
Name: omuchatprovider
Version: 0.3.2
Summary: Add your description here
Author-email: am230 <111672334+am230@users.noreply.github.com>
Requires-Python: >=3.12
Requires-Dist: aiohttp>=3.9.1
Requires-Dist: beautifulsoup4>=4.12.2
Requires-Dist: iwashi>=3.0.2
Requires-Dist: loguru>=0.7.2
Requires-Dist: lxml>=5.0.0
Requires-Dist: omuchat>=0.1.9
